Xcesionpackage/__init__.py
Xcesionpackage/lib2.py
Xcesionpackage-0.2.dist-info/METADATA
Xcesionpackage-0.2.dist-info/WHEEL
Xcesionpackage-0.2.dist-info/top_level.txt
Xcesionpackage-0.2.dist-info/RECORD
